litesearch/__init__.py
litesearch/_modidx.py
litesearch/core.py
litesearch/data.py
litesearch/postfix.py
litesearch/utils.py
litesearch-0.0.9.dist-info/licenses/LICENSE
litesearch-0.0.9.dist-info/METADATA
litesearch-0.0.9.dist-info/WHEEL
litesearch-0.0.9.dist-info/entry_points.txt
litesearch-0.0.9.dist-info/top_level.txt
litesearch-0.0.9.dist-info/RECORD
