Metadata-Version: 2.4
Name: litesearch
Version: 0.0.9
Summary: search through files with fts5, vectors and get reranked results. Fast
Home-page: https://github.com/Karthik777/litesearch
Author: 71293
Author-email: karthik.rajgopal@hotmail.com
License: Apache Software License 2.0
Keywords: nbdev jupyter notebook python
Classifier: Development Status :: 4 - Beta
Classifier: Intended Audience :: Developers
Classifier: Natural Language :: English
Classifier: Programming Language :: Python :: 3.10
Classifier: Programming Language :: Python :: 3.11
Classifier: Programming Language :: Python :: 3.12
Classifier: Programming Language :: Python :: 3.13
Classifier: License :: OSI Approved :: Apache Software License
Requires-Python: >=3.10
License-File: LICENSE
Requires-Dist: fastlite
Requires-Dist: usearch
Requires-Dist: yake
Requires-Dist: pymupdf
Requires-Dist: onnxruntime-gpu
Provides-Extra: dev
Requires-Dist: notebook; extra == "dev"
Requires-Dist: nbdev; extra == "dev"
Requires-Dist: jupyterlab; extra == "dev"
Requires-Dist: jupyterlab-quarto; extra == "dev"
Requires-Dist: selectolax; extra == "dev"
Requires-Dist: lisette; extra == "dev"
Requires-Dist: ddgs; extra == "dev"
Requires-Dist: pyperclip; extra == "dev"
Requires-Dist: chonkie; extra == "dev"
Requires-Dist: model2vec[distill]; extra == "dev"
Requires-Dist: flashrank; extra == "dev"
Dynamic: author
Dynamic: author-email
Dynamic: classifier
Dynamic: description
Dynamic: description-content-type
Dynamic: home-page
Dynamic: keywords
Dynamic: license
Dynamic: license-file
Dynamic: provides-extra
Dynamic: requires-dist
Dynamic: requires-python
Dynamic: summary
